tests/__init__.py
tests/data.py
tests/test_api.py
tests/test_jwt_auth.py
wcfmclient/__init__.py
wcfmclient/api.py
wcfmclient/jwt_auth_service.py
wcfmclient/session.py
wcfmclient-1.0.0.dist-info/LICENSE
wcfmclient-1.0.0.dist-info/METADATA
wcfmclient-1.0.0.dist-info/WHEEL
wcfmclient-1.0.0.dist-info/top_level.txt
wcfmclient-1.0.0.dist-info/RECORD
