Metadata-Version: 2.1
Name: wcfmclient
Version: 1.0.0
Summary: UNKNOWN
Home-page: UNKNOWN
Author: palanskiheji
License: UNKNOWN
Platform: UNKNOWN
Classifier: Programming Language :: Python :: 2.7
Classifier: Programming Language :: Python :: 3.6
Classifier: License :: OSI Approved :: MIT License
Classifier: Operating System :: OS Independent
Requires-Python: >=2.7,!=3.0.*,!=3.1.*
Requires-Dist: requests
